abv_py/__init__.py
abv_py/const/__init__.py
abv_py/util/__init__.py
abv_py-0.2.1.dist-info/LICENSE
abv_py-0.2.1.dist-info/METADATA
abv_py-0.2.1.dist-info/WHEEL
abv_py-0.2.1.dist-info/RECORD
