Metadata-Version: 2.1
Name: abv-py
Version: 0.2.1
Summary: bilibili AV/BV converter with avid>2^28 support
Home-page: https://github.com/poly000/abv-py
License: MIT
Author: poly000
Requires-Python: >=3.7,<4.0
Classifier: License :: OSI Approved :: MIT License
Classifier: Programming Language :: Python :: 3
Classifier: Programming Language :: Python :: 3.7
Classifier: Programming Language :: Python :: 3.8
Classifier: Programming Language :: Python :: 3.9
Classifier: Programming Language :: Python :: 3.10
Classifier: Programming Language :: Python :: 3.11
Classifier: Programming Language :: Python :: 3.12
Project-URL: Repository, https://github.com/poly000/abv-py
